{"epoch": 0, "test_accuracy": 46.05678233438486, "done": false, "timesteps_total": null, "episodes_total": null, "training_iteration": 1, "experiment_id": "1378192cf1f14be2b131e3f27a8c50d3", "date": "2022-04-06_03-46-34", "timestamp": 1649216794, "time_this_iter_s": 6.048099040985107, "time_total_s": 6.048099040985107, "pid": 94147, "hostname": "nvidia-gpu-cloud-tensorflow-image-8gpus-vm", "node_ip": "10.128.0.8", "config": {"num_anc": 1, "deph_p": 1, "tune_lr": 0, "tune_init_std": 0.1, "a": 1.0, "b": 50.0, "A": 10.0, "s": 5.0, "t": 3.0, "gamma": 0.002623630836479514}, "time_since_restore": 6.048099040985107, "timesteps_since_restore": 0, "iterations_since_restore": 1, "trial_id": "2097a057"}
{"epoch": 1, "test_accuracy": 53.25972660357519, "done": false, "timesteps_total": null, "episodes_total": null, "training_iteration": 2, "experiment_id": "1378192cf1f14be2b131e3f27a8c50d3", "date": "2022-04-06_03-46-36", "timestamp": 1649216796, "time_this_iter_s": 1.7804038524627686, "time_total_s": 7.828502893447876, "pid": 94147, "hostname": "nvidia-gpu-cloud-tensorflow-image-8gpus-vm", "node_ip": "10.128.0.8", "config": {"num_anc": 1, "deph_p": 1, "tune_lr": 0, "tune_init_std": 0.1, "a": 1.0, "b": 50.0, "A": 10.0, "s": 5.0, "t": 3.0, "gamma": 0.002623630836479514}, "time_since_restore": 7.828502893447876, "timesteps_since_restore": 0, "iterations_since_restore": 2, "trial_id": "2097a057"}
{"epoch": 2, "test_accuracy": 51.26182965299685, "done": false, "timesteps_total": null, "episodes_total": null, "training_iteration": 3, "experiment_id": "1378192cf1f14be2b131e3f27a8c50d3", "date": "2022-04-06_03-46-37", "timestamp": 1649216797, "time_this_iter_s": 1.7986102104187012, "time_total_s": 9.627113103866577, "pid": 94147, "hostname": "nvidia-gpu-cloud-tensorflow-image-8gpus-vm", "node_ip": "10.128.0.8", "config": {"num_anc": 1, "deph_p": 1, "tune_lr": 0, "tune_init_std": 0.1, "a": 1.0, "b": 50.0, "A": 10.0, "s": 5.0, "t": 3.0, "gamma": 0.002623630836479514}, "time_since_restore": 9.627113103866577, "timesteps_since_restore": 0, "iterations_since_restore": 3, "trial_id": "2097a057"}
{"epoch": 3, "test_accuracy": 52.10304942166141, "done": false, "timesteps_total": null, "episodes_total": null, "training_iteration": 4, "experiment_id": "1378192cf1f14be2b131e3f27a8c50d3", "date": "2022-04-06_03-46-39", "timestamp": 1649216799, "time_this_iter_s": 1.703401803970337, "time_total_s": 11.330514907836914, "pid": 94147, "hostname": "nvidia-gpu-cloud-tensorflow-image-8gpus-vm", "node_ip": "10.128.0.8", "config": {"num_anc": 1, "deph_p": 1, "tune_lr": 0, "tune_init_std": 0.1, "a": 1.0, "b": 50.0, "A": 10.0, "s": 5.0, "t": 3.0, "gamma": 0.002623630836479514}, "time_since_restore": 11.330514907836914, "timesteps_since_restore": 0, "iterations_since_restore": 4, "trial_id": "2097a057"}
{"epoch": 4, "test_accuracy": 52.83911671924291, "done": false, "timesteps_total": null, "episodes_total": null, "training_iteration": 5, "experiment_id": "1378192cf1f14be2b131e3f27a8c50d3", "date": "2022-04-06_03-46-41", "timestamp": 1649216801, "time_this_iter_s": 1.777719497680664, "time_total_s": 13.108234405517578, "pid": 94147, "hostname": "nvidia-gpu-cloud-tensorflow-image-8gpus-vm", "node_ip": "10.128.0.8", "config": {"num_anc": 1, "deph_p": 1, "tune_lr": 0, "tune_init_std": 0.1, "a": 1.0, "b": 50.0, "A": 10.0, "s": 5.0, "t": 3.0, "gamma": 0.002623630836479514}, "time_since_restore": 13.108234405517578, "timesteps_since_restore": 0, "iterations_since_restore": 5, "trial_id": "2097a057"}
{"epoch": 5, "test_accuracy": 53.10199789695058, "done": false, "timesteps_total": null, "episodes_total": null, "training_iteration": 6, "experiment_id": "1378192cf1f14be2b131e3f27a8c50d3", "date": "2022-04-06_03-46-43", "timestamp": 1649216803, "time_this_iter_s": 1.784851312637329, "time_total_s": 14.893085718154907, "pid": 94147, "hostname": "nvidia-gpu-cloud-tensorflow-image-8gpus-vm", "node_ip": "10.128.0.8", "config": {"num_anc": 1, "deph_p": 1, "tune_lr": 0, "tune_init_std": 0.1, "a": 1.0, "b": 50.0, "A": 10.0, "s": 5.0, "t": 3.0, "gamma": 0.002623630836479514}, "time_since_restore": 14.893085718154907, "timesteps_since_restore": 0, "iterations_since_restore": 6, "trial_id": "2097a057"}
{"epoch": 6, "test_accuracy": 53.10199789695058, "done": false, "timesteps_total": null, "episodes_total": null, "training_iteration": 7, "experiment_id": "1378192cf1f14be2b131e3f27a8c50d3", "date": "2022-04-06_03-46-45", "timestamp": 1649216805, "time_this_iter_s": 1.8049867153167725, "time_total_s": 16.69807243347168, "pid": 94147, "hostname": "nvidia-gpu-cloud-tensorflow-image-8gpus-vm", "node_ip": "10.128.0.8", "config": {"num_anc": 1, "deph_p": 1, "tune_lr": 0, "tune_init_std": 0.1, "a": 1.0, "b": 50.0, "A": 10.0, "s": 5.0, "t": 3.0, "gamma": 0.002623630836479514}, "time_since_restore": 16.69807243347168, "timesteps_since_restore": 0, "iterations_since_restore": 7, "trial_id": "2097a057"}
{"epoch": 7, "test_accuracy": 53.10199789695058, "done": false, "timesteps_total": null, "episodes_total": null, "training_iteration": 8, "experiment_id": "1378192cf1f14be2b131e3f27a8c50d3", "date": "2022-04-06_03-46-46", "timestamp": 1649216806, "time_this_iter_s": 1.7967865467071533, "time_total_s": 18.494858980178833, "pid": 94147, "hostname": "nvidia-gpu-cloud-tensorflow-image-8gpus-vm", "node_ip": "10.128.0.8", "config": {"num_anc": 1, "deph_p": 1, "tune_lr": 0, "tune_init_std": 0.1, "a": 1.0, "b": 50.0, "A": 10.0, "s": 5.0, "t": 3.0, "gamma": 0.002623630836479514}, "time_since_restore": 18.494858980178833, "timesteps_since_restore": 0, "iterations_since_restore": 8, "trial_id": "2097a057"}
{"epoch": 8, "test_accuracy": 53.10199789695058, "done": false, "timesteps_total": null, "episodes_total": null, "training_iteration": 9, "experiment_id": "1378192cf1f14be2b131e3f27a8c50d3", "date": "2022-04-06_03-46-48", "timestamp": 1649216808, "time_this_iter_s": 1.7880158424377441, "time_total_s": 20.282874822616577, "pid": 94147, "hostname": "nvidia-gpu-cloud-tensorflow-image-8gpus-vm", "node_ip": "10.128.0.8", "config": {"num_anc": 1, "deph_p": 1, "tune_lr": 0, "tune_init_std": 0.1, "a": 1.0, "b": 50.0, "A": 10.0, "s": 5.0, "t": 3.0, "gamma": 0.002623630836479514}, "time_since_restore": 20.282874822616577, "timesteps_since_restore": 0, "iterations_since_restore": 9, "trial_id": "2097a057"}
{"epoch": 9, "test_accuracy": 53.154574132492115, "done": false, "timesteps_total": null, "episodes_total": null, "training_iteration": 10, "experiment_id": "1378192cf1f14be2b131e3f27a8c50d3", "date": "2022-04-06_03-46-50", "timestamp": 1649216810, "time_this_iter_s": 1.7407212257385254, "time_total_s": 22.023596048355103, "pid": 94147, "hostname": "nvidia-gpu-cloud-tensorflow-image-8gpus-vm", "node_ip": "10.128.0.8", "config": {"num_anc": 1, "deph_p": 1, "tune_lr": 0, "tune_init_std": 0.1, "a": 1.0, "b": 50.0, "A": 10.0, "s": 5.0, "t": 3.0, "gamma": 0.002623630836479514}, "time_since_restore": 22.023596048355103, "timesteps_since_restore": 0, "iterations_since_restore": 10, "trial_id": "2097a057"}
{"epoch": 10, "test_accuracy": 52.99684542586751, "done": false, "timesteps_total": null, "episodes_total": null, "training_iteration": 11, "experiment_id": "1378192cf1f14be2b131e3f27a8c50d3", "date": "2022-04-06_03-46-52", "timestamp": 1649216812, "time_this_iter_s": 1.747750997543335, "time_total_s": 23.771347045898438, "pid": 94147, "hostname": "nvidia-gpu-cloud-tensorflow-image-8gpus-vm", "node_ip": "10.128.0.8", "config": {"num_anc": 1, "deph_p": 1, "tune_lr": 0, "tune_init_std": 0.1, "a": 1.0, "b": 50.0, "A": 10.0, "s": 5.0, "t": 3.0, "gamma": 0.002623630836479514}, "time_since_restore": 23.771347045898438, "timesteps_since_restore": 0, "iterations_since_restore": 11, "trial_id": "2097a057"}
{"epoch": 11, "test_accuracy": 52.52365930599369, "done": false, "timesteps_total": null, "episodes_total": null, "training_iteration": 12, "experiment_id": "1378192cf1f14be2b131e3f27a8c50d3", "date": "2022-04-06_03-46-53", "timestamp": 1649216813, "time_this_iter_s": 1.7372698783874512, "time_total_s": 25.50861692428589, "pid": 94147, "hostname": "nvidia-gpu-cloud-tensorflow-image-8gpus-vm", "node_ip": "10.128.0.8", "config": {"num_anc": 1, "deph_p": 1, "tune_lr": 0, "tune_init_std": 0.1, "a": 1.0, "b": 50.0, "A": 10.0, "s": 5.0, "t": 3.0, "gamma": 0.002623630836479514}, "time_since_restore": 25.50861692428589, "timesteps_since_restore": 0, "iterations_since_restore": 12, "trial_id": "2097a057"}
{"epoch": 12, "test_accuracy": 51.47213459516299, "done": false, "timesteps_total": null, "episodes_total": null, "training_iteration": 13, "experiment_id": "1378192cf1f14be2b131e3f27a8c50d3", "date": "2022-04-06_03-46-55", "timestamp": 1649216815, "time_this_iter_s": 1.6981234550476074, "time_total_s": 27.206740379333496, "pid": 94147, "hostname": "nvidia-gpu-cloud-tensorflow-image-8gpus-vm", "node_ip": "10.128.0.8", "config": {"num_anc": 1, "deph_p": 1, "tune_lr": 0, "tune_init_std": 0.1, "a": 1.0, "b": 50.0, "A": 10.0, "s": 5.0, "t": 3.0, "gamma": 0.002623630836479514}, "time_since_restore": 27.206740379333496, "timesteps_since_restore": 0, "iterations_since_restore": 13, "trial_id": "2097a057"}
{"epoch": 13, "test_accuracy": 53.04942166140905, "done": false, "timesteps_total": null, "episodes_total": null, "training_iteration": 14, "experiment_id": "1378192cf1f14be2b131e3f27a8c50d3", "date": "2022-04-06_03-46-57", "timestamp": 1649216817, "time_this_iter_s": 1.782555341720581, "time_total_s": 28.989295721054077, "pid": 94147, "hostname": "nvidia-gpu-cloud-tensorflow-image-8gpus-vm", "node_ip": "10.128.0.8", "config": {"num_anc": 1, "deph_p": 1, "tune_lr": 0, "tune_init_std": 0.1, "a": 1.0, "b": 50.0, "A": 10.0, "s": 5.0, "t": 3.0, "gamma": 0.002623630836479514}, "time_since_restore": 28.989295721054077, "timesteps_since_restore": 0, "iterations_since_restore": 14, "trial_id": "2097a057"}
{"epoch": 14, "test_accuracy": 53.04942166140905, "done": false, "timesteps_total": null, "episodes_total": null, "training_iteration": 15, "experiment_id": "1378192cf1f14be2b131e3f27a8c50d3", "date": "2022-04-06_03-46-59", "timestamp": 1649216819, "time_this_iter_s": 1.7598438262939453, "time_total_s": 30.749139547348022, "pid": 94147, "hostname": "nvidia-gpu-cloud-tensorflow-image-8gpus-vm", "node_ip": "10.128.0.8", "config": {"num_anc": 1, "deph_p": 1, "tune_lr": 0, "tune_init_std": 0.1, "a": 1.0, "b": 50.0, "A": 10.0, "s": 5.0, "t": 3.0, "gamma": 0.002623630836479514}, "time_since_restore": 30.749139547348022, "timesteps_since_restore": 0, "iterations_since_restore": 15, "trial_id": "2097a057"}
{"epoch": 15, "test_accuracy": 52.78654048370137, "done": false, "timesteps_total": null, "episodes_total": null, "training_iteration": 16, "experiment_id": "1378192cf1f14be2b131e3f27a8c50d3", "date": "2022-04-06_03-47-00", "timestamp": 1649216820, "time_this_iter_s": 1.7537262439727783, "time_total_s": 32.5028657913208, "pid": 94147, "hostname": "nvidia-gpu-cloud-tensorflow-image-8gpus-vm", "node_ip": "10.128.0.8", "config": {"num_anc": 1, "deph_p": 1, "tune_lr": 0, "tune_init_std": 0.1, "a": 1.0, "b": 50.0, "A": 10.0, "s": 5.0, "t": 3.0, "gamma": 0.002623630836479514}, "time_since_restore": 32.5028657913208, "timesteps_since_restore": 0, "iterations_since_restore": 16, "trial_id": "2097a057"}
{"epoch": 16, "test_accuracy": 51.89274447949527, "done": false, "timesteps_total": null, "episodes_total": null, "training_iteration": 17, "experiment_id": "1378192cf1f14be2b131e3f27a8c50d3", "date": "2022-04-06_03-47-02", "timestamp": 1649216822, "time_this_iter_s": 1.7700624465942383, "time_total_s": 34.27292823791504, "pid": 94147, "hostname": "nvidia-gpu-cloud-tensorflow-image-8gpus-vm", "node_ip": "10.128.0.8", "config": {"num_anc": 1, "deph_p": 1, "tune_lr": 0, "tune_init_std": 0.1, "a": 1.0, "b": 50.0, "A": 10.0, "s": 5.0, "t": 3.0, "gamma": 0.002623630836479514}, "time_since_restore": 34.27292823791504, "timesteps_since_restore": 0, "iterations_since_restore": 17, "trial_id": "2097a057"}
{"epoch": 17, "test_accuracy": 52.78654048370137, "done": false, "timesteps_total": null, "episodes_total": null, "training_iteration": 18, "experiment_id": "1378192cf1f14be2b131e3f27a8c50d3", "date": "2022-04-06_03-47-04", "timestamp": 1649216824, "time_this_iter_s": 1.7691540718078613, "time_total_s": 36.0420823097229, "pid": 94147, "hostname": "nvidia-gpu-cloud-tensorflow-image-8gpus-vm", "node_ip": "10.128.0.8", "config": {"num_anc": 1, "deph_p": 1, "tune_lr": 0, "tune_init_std": 0.1, "a": 1.0, "b": 50.0, "A": 10.0, "s": 5.0, "t": 3.0, "gamma": 0.002623630836479514}, "time_since_restore": 36.0420823097229, "timesteps_since_restore": 0, "iterations_since_restore": 18, "trial_id": "2097a057"}
{"epoch": 18, "test_accuracy": 53.154574132492115, "done": false, "timesteps_total": null, "episodes_total": null, "training_iteration": 19, "experiment_id": "1378192cf1f14be2b131e3f27a8c50d3", "date": "2022-04-06_03-47-06", "timestamp": 1649216826, "time_this_iter_s": 1.7819762229919434, "time_total_s": 37.824058532714844, "pid": 94147, "hostname": "nvidia-gpu-cloud-tensorflow-image-8gpus-vm", "node_ip": "10.128.0.8", "config": {"num_anc": 1, "deph_p": 1, "tune_lr": 0, "tune_init_std": 0.1, "a": 1.0, "b": 50.0, "A": 10.0, "s": 5.0, "t": 3.0, "gamma": 0.002623630836479514}, "time_since_restore": 37.824058532714844, "timesteps_since_restore": 0, "iterations_since_restore": 19, "trial_id": "2097a057"}
{"epoch": 19, "test_accuracy": 53.154574132492115, "done": false, "timesteps_total": null, "episodes_total": null, "training_iteration": 20, "experiment_id": "1378192cf1f14be2b131e3f27a8c50d3", "date": "2022-04-06_03-47-07", "timestamp": 1649216827, "time_this_iter_s": 1.690704107284546, "time_total_s": 39.51476263999939, "pid": 94147, "hostname": "nvidia-gpu-cloud-tensorflow-image-8gpus-vm", "node_ip": "10.128.0.8", "config": {"num_anc": 1, "deph_p": 1, "tune_lr": 0, "tune_init_std": 0.1, "a": 1.0, "b": 50.0, "A": 10.0, "s": 5.0, "t": 3.0, "gamma": 0.002623630836479514}, "time_since_restore": 39.51476263999939, "timesteps_since_restore": 0, "iterations_since_restore": 20, "trial_id": "2097a057"}
{"epoch": 20, "test_accuracy": 47.05573080967403, "done": false, "timesteps_total": null, "episodes_total": null, "training_iteration": 21, "experiment_id": "1378192cf1f14be2b131e3f27a8c50d3", "date": "2022-04-06_03-47-09", "timestamp": 1649216829, "time_this_iter_s": 1.7759730815887451, "time_total_s": 41.290735721588135, "pid": 94147, "hostname": "nvidia-gpu-cloud-tensorflow-image-8gpus-vm", "node_ip": "10.128.0.8", "config": {"num_anc": 1, "deph_p": 1, "tune_lr": 0, "tune_init_std": 0.1, "a": 1.0, "b": 50.0, "A": 10.0, "s": 5.0, "t": 3.0, "gamma": 0.002623630836479514}, "time_since_restore": 41.290735721588135, "timesteps_since_restore": 0, "iterations_since_restore": 21, "trial_id": "2097a057"}
{"epoch": 21, "test_accuracy": 38.85383806519454, "done": false, "timesteps_total": null, "episodes_total": null, "training_iteration": 22, "experiment_id": "1378192cf1f14be2b131e3f27a8c50d3", "date": "2022-04-06_03-47-10", "timestamp": 1649216830, "time_this_iter_s": 1.2453522682189941, "time_total_s": 42.53608798980713, "pid": 94147, "hostname": "nvidia-gpu-cloud-tensorflow-image-8gpus-vm", "node_ip": "10.128.0.8", "config": {"num_anc": 1, "deph_p": 1, "tune_lr": 0, "tune_init_std": 0.1, "a": 1.0, "b": 50.0, "A": 10.0, "s": 5.0, "t": 3.0, "gamma": 0.002623630836479514}, "time_since_restore": 42.53608798980713, "timesteps_since_restore": 0, "iterations_since_restore": 22, "trial_id": "2097a057"}
{"epoch": 22, "test_accuracy": 43.007360672975814, "done": false, "timesteps_total": null, "episodes_total": null, "training_iteration": 23, "experiment_id": "1378192cf1f14be2b131e3f27a8c50d3", "date": "2022-04-06_03-47-11", "timestamp": 1649216831, "time_this_iter_s": 0.6863594055175781, "time_total_s": 43.22244739532471, "pid": 94147, "hostname": "nvidia-gpu-cloud-tensorflow-image-8gpus-vm", "node_ip": "10.128.0.8", "config": {"num_anc": 1, "deph_p": 1, "tune_lr": 0, "tune_init_std": 0.1, "a": 1.0, "b": 50.0, "A": 10.0, "s": 5.0, "t": 3.0, "gamma": 0.002623630836479514}, "time_since_restore": 43.22244739532471, "timesteps_since_restore": 0, "iterations_since_restore": 23, "trial_id": "2097a057"}
{"epoch": 23, "test_accuracy": 37.960042060988435, "done": false, "timesteps_total": null, "episodes_total": null, "training_iteration": 24, "experiment_id": "1378192cf1f14be2b131e3f27a8c50d3", "date": "2022-04-06_03-47-12", "timestamp": 1649216832, "time_this_iter_s": 0.6939065456390381, "time_total_s": 43.916353940963745, "pid": 94147, "hostname": "nvidia-gpu-cloud-tensorflow-image-8gpus-vm", "node_ip": "10.128.0.8", "config": {"num_anc": 1, "deph_p": 1, "tune_lr": 0, "tune_init_std": 0.1, "a": 1.0, "b": 50.0, "A": 10.0, "s": 5.0, "t": 3.0, "gamma": 0.002623630836479514}, "time_since_restore": 43.916353940963745, "timesteps_since_restore": 0, "iterations_since_restore": 24, "trial_id": "2097a057"}
{"epoch": 24, "test_accuracy": 40.01051524710831, "done": false, "timesteps_total": null, "episodes_total": null, "training_iteration": 25, "experiment_id": "1378192cf1f14be2b131e3f27a8c50d3", "date": "2022-04-06_03-47-13", "timestamp": 1649216833, "time_this_iter_s": 0.6890296936035156, "time_total_s": 44.60538363456726, "pid": 94147, "hostname": "nvidia-gpu-cloud-tensorflow-image-8gpus-vm", "node_ip": "10.128.0.8", "config": {"num_anc": 1, "deph_p": 1, "tune_lr": 0, "tune_init_std": 0.1, "a": 1.0, "b": 50.0, "A": 10.0, "s": 5.0, "t": 3.0, "gamma": 0.002623630836479514}, "time_since_restore": 44.60538363456726, "timesteps_since_restore": 0, "iterations_since_restore": 25, "trial_id": "2097a057"}
{"epoch": 25, "test_accuracy": 39.95793901156677, "done": false, "timesteps_total": null, "episodes_total": null, "training_iteration": 26, "experiment_id": "1378192cf1f14be2b131e3f27a8c50d3", "date": "2022-04-06_03-47-13", "timestamp": 1649216833, "time_this_iter_s": 0.6894705295562744, "time_total_s": 45.294854164123535, "pid": 94147, "hostname": "nvidia-gpu-cloud-tensorflow-image-8gpus-vm", "node_ip": "10.128.0.8", "config": {"num_anc": 1, "deph_p": 1, "tune_lr": 0, "tune_init_std": 0.1, "a": 1.0, "b": 50.0, "A": 10.0, "s": 5.0, "t": 3.0, "gamma": 0.002623630836479514}, "time_since_restore": 45.294854164123535, "timesteps_since_restore": 0, "iterations_since_restore": 26, "trial_id": "2097a057"}
{"epoch": 26, "test_accuracy": 41.27234490010515, "done": false, "timesteps_total": null, "episodes_total": null, "training_iteration": 27, "experiment_id": "1378192cf1f14be2b131e3f27a8c50d3", "date": "2022-04-06_03-47-14", "timestamp": 1649216834, "time_this_iter_s": 0.6883344650268555, "time_total_s": 45.98318862915039, "pid": 94147, "hostname": "nvidia-gpu-cloud-tensorflow-image-8gpus-vm", "node_ip": "10.128.0.8", "config": {"num_anc": 1, "deph_p": 1, "tune_lr": 0, "tune_init_std": 0.1, "a": 1.0, "b": 50.0, "A": 10.0, "s": 5.0, "t": 3.0, "gamma": 0.002623630836479514}, "time_since_restore": 45.98318862915039, "timesteps_since_restore": 0, "iterations_since_restore": 27, "trial_id": "2097a057"}
{"epoch": 27, "test_accuracy": 39.27444794952682, "done": false, "timesteps_total": null, "episodes_total": null, "training_iteration": 28, "experiment_id": "1378192cf1f14be2b131e3f27a8c50d3", "date": "2022-04-06_03-47-15", "timestamp": 1649216835, "time_this_iter_s": 0.6847131252288818, "time_total_s": 46.66790175437927, "pid": 94147, "hostname": "nvidia-gpu-cloud-tensorflow-image-8gpus-vm", "node_ip": "10.128.0.8", "config": {"num_anc": 1, "deph_p": 1, "tune_lr": 0, "tune_init_std": 0.1, "a": 1.0, "b": 50.0, "A": 10.0, "s": 5.0, "t": 3.0, "gamma": 0.002623630836479514}, "time_since_restore": 46.66790175437927, "timesteps_since_restore": 0, "iterations_since_restore": 28, "trial_id": "2097a057"}
{"epoch": 28, "test_accuracy": 39.01156677181914, "done": false, "timesteps_total": null, "episodes_total": null, "training_iteration": 29, "experiment_id": "1378192cf1f14be2b131e3f27a8c50d3", "date": "2022-04-06_03-47-15", "timestamp": 1649216835, "time_this_iter_s": 0.684363842010498, "time_total_s": 47.35226559638977, "pid": 94147, "hostname": "nvidia-gpu-cloud-tensorflow-image-8gpus-vm", "node_ip": "10.128.0.8", "config": {"num_anc": 1, "deph_p": 1, "tune_lr": 0, "tune_init_std": 0.1, "a": 1.0, "b": 50.0, "A": 10.0, "s": 5.0, "t": 3.0, "gamma": 0.002623630836479514}, "time_since_restore": 47.35226559638977, "timesteps_since_restore": 0, "iterations_since_restore": 29, "trial_id": "2097a057"}
{"epoch": 29, "test_accuracy": 39.01156677181914, "done": false, "timesteps_total": null, "episodes_total": null, "training_iteration": 30, "experiment_id": "1378192cf1f14be2b131e3f27a8c50d3", "date": "2022-04-06_03-47-16", "timestamp": 1649216836, "time_this_iter_s": 0.6873793601989746, "time_total_s": 48.039644956588745, "pid": 94147, "hostname": "nvidia-gpu-cloud-tensorflow-image-8gpus-vm", "node_ip": "10.128.0.8", "config": {"num_anc": 1, "deph_p": 1, "tune_lr": 0, "tune_init_std": 0.1, "a": 1.0, "b": 50.0, "A": 10.0, "s": 5.0, "t": 3.0, "gamma": 0.002623630836479514}, "time_since_restore": 48.039644956588745, "timesteps_since_restore": 0, "iterations_since_restore": 30, "trial_id": "2097a057"}
{"epoch": 30, "test_accuracy": 39.58990536277602, "done": false, "timesteps_total": null, "episodes_total": null, "training_iteration": 31, "experiment_id": "1378192cf1f14be2b131e3f27a8c50d3", "date": "2022-04-06_03-47-17", "timestamp": 1649216837, "time_this_iter_s": 1.4519481658935547, "time_total_s": 49.4915931224823, "pid": 94147, "hostname": "nvidia-gpu-cloud-tensorflow-image-8gpus-vm", "node_ip": "10.128.0.8", "config": {"num_anc": 1, "deph_p": 1, "tune_lr": 0, "tune_init_std": 0.1, "a": 1.0, "b": 50.0, "A": 10.0, "s": 5.0, "t": 3.0, "gamma": 0.002623630836479514}, "time_since_restore": 49.4915931224823, "timesteps_since_restore": 0, "iterations_since_restore": 31, "trial_id": "2097a057"}
{"epoch": 31, "test_accuracy": 41.430073606729756, "done": false, "timesteps_total": null, "episodes_total": null, "training_iteration": 32, "experiment_id": "1378192cf1f14be2b131e3f27a8c50d3", "date": "2022-04-06_03-47-19", "timestamp": 1649216839, "time_this_iter_s": 1.7846360206604004, "time_total_s": 51.2762291431427, "pid": 94147, "hostname": "nvidia-gpu-cloud-tensorflow-image-8gpus-vm", "node_ip": "10.128.0.8", "config": {"num_anc": 1, "deph_p": 1, "tune_lr": 0, "tune_init_std": 0.1, "a": 1.0, "b": 50.0, "A": 10.0, "s": 5.0, "t": 3.0, "gamma": 0.002623630836479514}, "time_since_restore": 51.2762291431427, "timesteps_since_restore": 0, "iterations_since_restore": 32, "trial_id": "2097a057"}
{"epoch": 32, "test_accuracy": 39.22187171398528, "done": false, "timesteps_total": null, "episodes_total": null, "training_iteration": 33, "experiment_id": "1378192cf1f14be2b131e3f27a8c50d3", "date": "2022-04-06_03-47-21", "timestamp": 1649216841, "time_this_iter_s": 1.7806422710418701, "time_total_s": 53.05687141418457, "pid": 94147, "hostname": "nvidia-gpu-cloud-tensorflow-image-8gpus-vm", "node_ip": "10.128.0.8", "config": {"num_anc": 1, "deph_p": 1, "tune_lr": 0, "tune_init_std": 0.1, "a": 1.0, "b": 50.0, "A": 10.0, "s": 5.0, "t": 3.0, "gamma": 0.002623630836479514}, "time_since_restore": 53.05687141418457, "timesteps_since_restore": 0, "iterations_since_restore": 33, "trial_id": "2097a057"}
{"epoch": 33, "test_accuracy": 40.79915878023134, "done": false, "timesteps_total": null, "episodes_total": null, "training_iteration": 34, "experiment_id": "1378192cf1f14be2b131e3f27a8c50d3", "date": "2022-04-06_03-47-23", "timestamp": 1649216843, "time_this_iter_s": 1.8016810417175293, "time_total_s": 54.8585524559021, "pid": 94147, "hostname": "nvidia-gpu-cloud-tensorflow-image-8gpus-vm", "node_ip": "10.128.0.8", "config": {"num_anc": 1, "deph_p": 1, "tune_lr": 0, "tune_init_std": 0.1, "a": 1.0, "b": 50.0, "A": 10.0, "s": 5.0, "t": 3.0, "gamma": 0.002623630836479514}, "time_since_restore": 54.8585524559021, "timesteps_since_restore": 0, "iterations_since_restore": 34, "trial_id": "2097a057"}
{"epoch": 34, "test_accuracy": 41.53522607781283, "done": false, "timesteps_total": null, "episodes_total": null, "training_iteration": 35, "experiment_id": "1378192cf1f14be2b131e3f27a8c50d3", "date": "2022-04-06_03-47-25", "timestamp": 1649216845, "time_this_iter_s": 1.9737508296966553, "time_total_s": 56.832303285598755, "pid": 94147, "hostname": "nvidia-gpu-cloud-tensorflow-image-8gpus-vm", "node_ip": "10.128.0.8", "config": {"num_anc": 1, "deph_p": 1, "tune_lr": 0, "tune_init_std": 0.1, "a": 1.0, "b": 50.0, "A": 10.0, "s": 5.0, "t": 3.0, "gamma": 0.002623630836479514}, "time_since_restore": 56.832303285598755, "timesteps_since_restore": 0, "iterations_since_restore": 35, "trial_id": "2097a057"}
{"epoch": 35, "test_accuracy": 51.419558359621455, "done": false, "timesteps_total": null, "episodes_total": null, "training_iteration": 36, "experiment_id": "1378192cf1f14be2b131e3f27a8c50d3", "date": "2022-04-06_03-47-26", "timestamp": 1649216846, "time_this_iter_s": 1.6102721691131592, "time_total_s": 58.442575454711914, "pid": 94147, "hostname": "nvidia-gpu-cloud-tensorflow-image-8gpus-vm", "node_ip": "10.128.0.8", "config": {"num_anc": 1, "deph_p": 1, "tune_lr": 0, "tune_init_std": 0.1, "a": 1.0, "b": 50.0, "A": 10.0, "s": 5.0, "t": 3.0, "gamma": 0.002623630836479514}, "time_since_restore": 58.442575454711914, "timesteps_since_restore": 0, "iterations_since_restore": 36, "trial_id": "2097a057"}
{"epoch": 36, "test_accuracy": 47.89695057833859, "done": false, "timesteps_total": null, "episodes_total": null, "training_iteration": 37, "experiment_id": "1378192cf1f14be2b131e3f27a8c50d3", "date": "2022-04-06_03-47-28", "timestamp": 1649216848, "time_this_iter_s": 1.3897182941436768, "time_total_s": 59.83229374885559, "pid": 94147, "hostname": "nvidia-gpu-cloud-tensorflow-image-8gpus-vm", "node_ip": "10.128.0.8", "config": {"num_anc": 1, "deph_p": 1, "tune_lr": 0, "tune_init_std": 0.1, "a": 1.0, "b": 50.0, "A": 10.0, "s": 5.0, "t": 3.0, "gamma": 0.002623630836479514}, "time_since_restore": 59.83229374885559, "timesteps_since_restore": 0, "iterations_since_restore": 37, "trial_id": "2097a057"}
{"epoch": 37, "test_accuracy": 52.99684542586751, "done": false, "timesteps_total": null, "episodes_total": null, "training_iteration": 38, "experiment_id": "1378192cf1f14be2b131e3f27a8c50d3", "date": "2022-04-06_03-47-30", "timestamp": 1649216850, "time_this_iter_s": 1.7941431999206543, "time_total_s": 61.626436948776245, "pid": 94147, "hostname": "nvidia-gpu-cloud-tensorflow-image-8gpus-vm", "node_ip": "10.128.0.8", "config": {"num_anc": 1, "deph_p": 1, "tune_lr": 0, "tune_init_std": 0.1, "a": 1.0, "b": 50.0, "A": 10.0, "s": 5.0, "t": 3.0, "gamma": 0.002623630836479514}, "time_since_restore": 61.626436948776245, "timesteps_since_restore": 0, "iterations_since_restore": 38, "trial_id": "2097a057"}
{"epoch": 38, "test_accuracy": 53.10199789695058, "done": false, "timesteps_total": null, "episodes_total": null, "training_iteration": 39, "experiment_id": "1378192cf1f14be2b131e3f27a8c50d3", "date": "2022-04-06_03-47-31", "timestamp": 1649216851, "time_this_iter_s": 1.6543197631835938, "time_total_s": 63.28075671195984, "pid": 94147, "hostname": "nvidia-gpu-cloud-tensorflow-image-8gpus-vm", "node_ip": "10.128.0.8", "config": {"num_anc": 1, "deph_p": 1, "tune_lr": 0, "tune_init_std": 0.1, "a": 1.0, "b": 50.0, "A": 10.0, "s": 5.0, "t": 3.0, "gamma": 0.002623630836479514}, "time_since_restore": 63.28075671195984, "timesteps_since_restore": 0, "iterations_since_restore": 39, "trial_id": "2097a057"}
{"epoch": 39, "test_accuracy": 52.99684542586751, "done": false, "timesteps_total": null, "episodes_total": null, "training_iteration": 40, "experiment_id": "1378192cf1f14be2b131e3f27a8c50d3", "date": "2022-04-06_03-47-33", "timestamp": 1649216853, "time_this_iter_s": 1.7780580520629883, "time_total_s": 65.05881476402283, "pid": 94147, "hostname": "nvidia-gpu-cloud-tensorflow-image-8gpus-vm", "node_ip": "10.128.0.8", "config": {"num_anc": 1, "deph_p": 1, "tune_lr": 0, "tune_init_std": 0.1, "a": 1.0, "b": 50.0, "A": 10.0, "s": 5.0, "t": 3.0, "gamma": 0.002623630836479514}, "time_since_restore": 65.05881476402283, "timesteps_since_restore": 0, "iterations_since_restore": 40, "trial_id": "2097a057"}
{"epoch": 40, "test_accuracy": 52.83911671924291, "done": false, "timesteps_total": null, "episodes_total": null, "training_iteration": 41, "experiment_id": "1378192cf1f14be2b131e3f27a8c50d3", "date": "2022-04-06_03-47-35", "timestamp": 1649216855, "time_this_iter_s": 1.6348190307617188, "time_total_s": 66.69363379478455, "pid": 94147, "hostname": "nvidia-gpu-cloud-tensorflow-image-8gpus-vm", "node_ip": "10.128.0.8", "config": {"num_anc": 1, "deph_p": 1, "tune_lr": 0, "tune_init_std": 0.1, "a": 1.0, "b": 50.0, "A": 10.0, "s": 5.0, "t": 3.0, "gamma": 0.002623630836479514}, "time_since_restore": 66.69363379478455, "timesteps_since_restore": 0, "iterations_since_restore": 41, "trial_id": "2097a057"}
{"epoch": 41, "test_accuracy": 52.6813880126183, "done": false, "timesteps_total": null, "episodes_total": null, "training_iteration": 42, "experiment_id": "1378192cf1f14be2b131e3f27a8c50d3", "date": "2022-04-06_03-47-36", "timestamp": 1649216856, "time_this_iter_s": 1.7756602764129639, "time_total_s": 68.46929407119751, "pid": 94147, "hostname": "nvidia-gpu-cloud-tensorflow-image-8gpus-vm", "node_ip": "10.128.0.8", "config": {"num_anc": 1, "deph_p": 1, "tune_lr": 0, "tune_init_std": 0.1, "a": 1.0, "b": 50.0, "A": 10.0, "s": 5.0, "t": 3.0, "gamma": 0.002623630836479514}, "time_since_restore": 68.46929407119751, "timesteps_since_restore": 0, "iterations_since_restore": 42, "trial_id": "2097a057"}
{"epoch": 42, "test_accuracy": 52.15562565720294, "done": false, "timesteps_total": null, "episodes_total": null, "training_iteration": 43, "experiment_id": "1378192cf1f14be2b131e3f27a8c50d3", "date": "2022-04-06_03-47-38", "timestamp": 1649216858, "time_this_iter_s": 1.6589629650115967, "time_total_s": 70.1282570362091, "pid": 94147, "hostname": "nvidia-gpu-cloud-tensorflow-image-8gpus-vm", "node_ip": "10.128.0.8", "config": {"num_anc": 1, "deph_p": 1, "tune_lr": 0, "tune_init_std": 0.1, "a": 1.0, "b": 50.0, "A": 10.0, "s": 5.0, "t": 3.0, "gamma": 0.002623630836479514}, "time_since_restore": 70.1282570362091, "timesteps_since_restore": 0, "iterations_since_restore": 43, "trial_id": "2097a057"}
{"epoch": 43, "test_accuracy": 53.154574132492115, "done": false, "timesteps_total": null, "episodes_total": null, "training_iteration": 44, "experiment_id": "1378192cf1f14be2b131e3f27a8c50d3", "date": "2022-04-06_03-47-40", "timestamp": 1649216860, "time_this_iter_s": 1.7667136192321777, "time_total_s": 71.89497065544128, "pid": 94147, "hostname": "nvidia-gpu-cloud-tensorflow-image-8gpus-vm", "node_ip": "10.128.0.8", "config": {"num_anc": 1, "deph_p": 1, "tune_lr": 0, "tune_init_std": 0.1, "a": 1.0, "b": 50.0, "A": 10.0, "s": 5.0, "t": 3.0, "gamma": 0.002623630836479514}, "time_since_restore": 71.89497065544128, "timesteps_since_restore": 0, "iterations_since_restore": 44, "trial_id": "2097a057"}
{"epoch": 44, "test_accuracy": 52.52365930599369, "done": false, "timesteps_total": null, "episodes_total": null, "training_iteration": 45, "experiment_id": "1378192cf1f14be2b131e3f27a8c50d3", "date": "2022-04-06_03-47-42", "timestamp": 1649216862, "time_this_iter_s": 1.7045912742614746, "time_total_s": 73.59956192970276, "pid": 94147, "hostname": "nvidia-gpu-cloud-tensorflow-image-8gpus-vm", "node_ip": "10.128.0.8", "config": {"num_anc": 1, "deph_p": 1, "tune_lr": 0, "tune_init_std": 0.1, "a": 1.0, "b": 50.0, "A": 10.0, "s": 5.0, "t": 3.0, "gamma": 0.002623630836479514}, "time_since_restore": 73.59956192970276, "timesteps_since_restore": 0, "iterations_since_restore": 45, "trial_id": "2097a057"}
{"epoch": 45, "test_accuracy": 52.10304942166141, "done": false, "timesteps_total": null, "episodes_total": null, "training_iteration": 46, "experiment_id": "1378192cf1f14be2b131e3f27a8c50d3", "date": "2022-04-06_03-47-43", "timestamp": 1649216863, "time_this_iter_s": 1.6986932754516602, "time_total_s": 75.29825520515442, "pid": 94147, "hostname": "nvidia-gpu-cloud-tensorflow-image-8gpus-vm", "node_ip": "10.128.0.8", "config": {"num_anc": 1, "deph_p": 1, "tune_lr": 0, "tune_init_std": 0.1, "a": 1.0, "b": 50.0, "A": 10.0, "s": 5.0, "t": 3.0, "gamma": 0.002623630836479514}, "time_since_restore": 75.29825520515442, "timesteps_since_restore": 0, "iterations_since_restore": 46, "trial_id": "2097a057"}
{"epoch": 46, "test_accuracy": 52.99684542586751, "done": false, "timesteps_total": null, "episodes_total": null, "training_iteration": 47, "experiment_id": "1378192cf1f14be2b131e3f27a8c50d3", "date": "2022-04-06_03-47-45", "timestamp": 1649216865, "time_this_iter_s": 1.5240826606750488, "time_total_s": 76.82233786582947, "pid": 94147, "hostname": "nvidia-gpu-cloud-tensorflow-image-8gpus-vm", "node_ip": "10.128.0.8", "config": {"num_anc": 1, "deph_p": 1, "tune_lr": 0, "tune_init_std": 0.1, "a": 1.0, "b": 50.0, "A": 10.0, "s": 5.0, "t": 3.0, "gamma": 0.002623630836479514}, "time_since_restore": 76.82233786582947, "timesteps_since_restore": 0, "iterations_since_restore": 47, "trial_id": "2097a057"}
{"epoch": 47, "test_accuracy": 52.99684542586751, "done": false, "timesteps_total": null, "episodes_total": null, "training_iteration": 48, "experiment_id": "1378192cf1f14be2b131e3f27a8c50d3", "date": "2022-04-06_03-47-47", "timestamp": 1649216867, "time_this_iter_s": 1.7832696437835693, "time_total_s": 78.60560750961304, "pid": 94147, "hostname": "nvidia-gpu-cloud-tensorflow-image-8gpus-vm", "node_ip": "10.128.0.8", "config": {"num_anc": 1, "deph_p": 1, "tune_lr": 0, "tune_init_std": 0.1, "a": 1.0, "b": 50.0, "A": 10.0, "s": 5.0, "t": 3.0, "gamma": 0.002623630836479514}, "time_since_restore": 78.60560750961304, "timesteps_since_restore": 0, "iterations_since_restore": 48, "trial_id": "2097a057"}
{"epoch": 48, "test_accuracy": 46.05678233438486, "done": false, "timesteps_total": null, "episodes_total": null, "training_iteration": 49, "experiment_id": "1378192cf1f14be2b131e3f27a8c50d3", "date": "2022-04-06_03-47-48", "timestamp": 1649216868, "time_this_iter_s": 1.6354091167449951, "time_total_s": 80.24101662635803, "pid": 94147, "hostname": "nvidia-gpu-cloud-tensorflow-image-8gpus-vm", "node_ip": "10.128.0.8", "config": {"num_anc": 1, "deph_p": 1, "tune_lr": 0, "tune_init_std": 0.1, "a": 1.0, "b": 50.0, "A": 10.0, "s": 5.0, "t": 3.0, "gamma": 0.002623630836479514}, "time_since_restore": 80.24101662635803, "timesteps_since_restore": 0, "iterations_since_restore": 49, "trial_id": "2097a057"}
{"epoch": 49, "test_accuracy": 39.327024185068346, "done": true, "timesteps_total": null, "episodes_total": null, "training_iteration": 50, "experiment_id": "1378192cf1f14be2b131e3f27a8c50d3", "date": "2022-04-06_03-47-50", "timestamp": 1649216870, "time_this_iter_s": 1.783661127090454, "time_total_s": 82.02467775344849, "pid": 94147, "hostname": "nvidia-gpu-cloud-tensorflow-image-8gpus-vm", "node_ip": "10.128.0.8", "config": {"num_anc": 1, "deph_p": 1, "tune_lr": 0, "tune_init_std": 0.1, "a": 1.0, "b": 50.0, "A": 10.0, "s": 5.0, "t": 3.0, "gamma": 0.002623630836479514}, "time_since_restore": 82.02467775344849, "timesteps_since_restore": 0, "iterations_since_restore": 50, "trial_id": "2097a057"}
